krill-0.3.0.dist-info/entry_points.txt
krill-0.3.0.dist-info/DESCRIPTION.rst
krill-0.3.0.dist-info/metadata.json
krill-0.3.0.dist-info/RECORD
krill-0.3.0.dist-info/METADATA
krill-0.3.0.dist-info/top_level.txt
krill-0.3.0.dist-info/WHEEL
krill/__init__.py
krill/krill.py
