Metadata-Version: 2.0
Name: krill
Version: 0.3.0
Summary: Read and filter web feeds
Home-page: https://github.com/p-e-w/krill
Author: Philipp Emanuel Weidmann
Author-email: pew@worldwidemann.com
License: GPLv3
Keywords: news feed rss atom twitter
Platform: UNKNOWN
Classifier: Development Status :: 3 - Alpha
Classifier: Intended Audience :: End Users/Desktop
Classifier: Topic :: Internet :: WWW/HTTP :: Dynamic Content :: News/Diary
Classifier: License :: OSI Approved :: GNU General Public License v3 (GPLv3)
Classifier: Programming Language :: Python :: 2
Classifier: Programming Language :: Python :: 2.7
Classifier: Programming Language :: Python :: 3
Classifier: Programming Language :: Python :: 3.2
Classifier: Programming Language :: Python :: 3.3
Classifier: Programming Language :: Python :: 3.4
Requires-Dist: beautifulsoup4
Requires-Dist: feedparser
Requires-Dist: blessings
